{
  "project_info": {
    "project_number": "302094454019",
    "firebase_url": "https://pear-50a28.firebaseio.com",
    "project_id": "pear-50a28",
    "storage_bucket": "pear-50a28.appspot.com"
  },
  "client": [
    {
      "client_info": {
        "mobilesdk_app_id": "1:302094454019:android:7e6a05ced003f3a5",
        "android_client_info": {
          "package_name": "com.pearsquad.pear"
        }
      },
      "oauth_client": [
        {
          "client_id": "302094454019-vq71r2ht7ofdocoev5qp01tnl5bqhdnu.apps.googleusercontent.com",
          "client_type": 3
        }
      ],
      "api_key": [
        {
          "current_key": "AIzaSyBTXbdWl9I27Vbn46CI6c3LaK0Bynq421k"
        }
      ],
      "services": {
        "analytics_service": {
          "status": 1
        },
        "appinvite_service": {
          "status": 1,
          "other_platform_oauth_client": []
        },
        "ads_service": {
          "status": 2
        }
      }
    }
  ],
  "configuration_version": "1"
}